elo_rating/__init__.py
elo_rating-0.0.1.dist-info/METADATA
elo_rating-0.0.1.dist-info/WHEEL
elo_rating-0.0.1.dist-info/top_level.txt
elo_rating-0.0.1.dist-info/RECORD
