Metadata-Version: 2.1
Name: elo-rating
Version: 0.0.1
Summary: An implementation of Elo rating system for use in comparative crowdsourcing tasks
Author-email: Hasti Narimanzadeh <hasti.nz@gmail.com>
License: MIT
Keywords: Elo,Crowdsourcing,Ranking
Classifier: Development Status :: 3 - Alpha
Classifier: Intended Audience :: Education
Classifier: Intended Audience :: Science/Research
Classifier: License :: OSI Approved :: MIT License
Classifier: Programming Language :: Python :: 3
Classifier: Topic :: Scientific/Engineering :: Information Analysis
Requires-Python: >=3.8
